[
  {
    "scene_idx": 0,
    "kind": "start",
    "path": "output/Module_6__8_Exercises/frames/scene_0000_start.jpg",
    "time": 0.2,
    "width": 1920,
    "height": 1080
  },
  {
    "scene_idx": 0,
    "kind": "mid",
    "path": "output/Module_6__8_Exercises/frames/scene_0000_mid.jpg",
    "time": 55.78,
    "width": 1920,
    "height": 1080
  },
  {
    "scene_idx": 0,
    "kind": "end",
    "path": "output/Module_6__8_Exercises/frames/scene_0000_end.jpg",
    "time": 111.36,
    "width": 1920,
    "height": 1080
  }
]